[
    {
        "status": "completed", 
        "check_run_url": "https://api.github.com/repos/drodin-tests/hunter/check-runs/1054969873", 
        "name": "libogg analyze-cxx17 ubuntu-16.04", 
        "run_id": 233928809, 
        "url": "https://api.github.com/repos/drodin-tests/hunter/actions/jobs/1054969873", 
        "html_url": "https://github.com/drodin-tests/hunter/runs/1054969873", 
        "completed_at": "2020-09-01T07:19:53Z", 
        "run_url": "https://api.github.com/repos/drodin-tests/hunter/actions/runs/233928809", 
        "node_id": "MDg6Q2hlY2tSdW4xMDU0OTY5ODcz", 
        "steps": [
            {
                "status": "completed", 
                "name": "Set up job", 
                "number": 1, 
                "completed_at": "2020-09-01T07:19:28.000Z", 
                "started_at": "2020-09-01T07:19:25.000Z", 
                "conclusion": "success"
            }, 
            {
                "status": "completed", 
                "name": "Git checkout with submodules", 
                "number": 2, 
                "completed_at": "2020-09-01T07:19:32.000Z", 
                "started_at": "2020-09-01T07:19:28.000Z", 
                "conclusion": "success"
            }, 
            {
                "status": "completed", 
                "name": "Set up Python", 
                "number": 3, 
                "completed_at": "2020-09-01T07:19:32.000Z", 
                "started_at": "2020-09-01T07:19:32.000Z", 
                "conclusion": "success"
            }, 
            {
                "status": "completed", 
                "name": "Upgrade pip", 
                "number": 4, 
                "completed_at": "2020-09-01T07:19:33.000Z", 
                "started_at": "2020-09-01T07:19:32.000Z", 
                "conclusion": "success"
            }, 
            {
                "status": "completed", 
                "name": "Build on Unix", 
                "number": 5, 
                "completed_at": "2020-09-01T07:19:53.000Z", 
                "started_at": "2020-09-01T07:19:33.000Z", 
                "conclusion": "failure"
            }, 
            {
                "status": "completed", 
                "name": "Build on Windows", 
                "number": 6, 
                "completed_at": "2020-09-01T07:19:53.000Z", 
                "started_at": "2020-09-01T07:19:53.000Z", 
                "conclusion": "skipped"
            }, 
            {
                "status": "completed", 
                "name": "Post Git checkout with submodules", 
                "number": 12, 
                "completed_at": "2020-09-01T07:19:53.000Z", 
                "started_at": "2020-09-01T07:19:53.000Z", 
                "conclusion": "success"
            }, 
            {
                "status": "completed", 
                "name": "Complete job", 
                "number": 13, 
                "completed_at": "2020-09-01T07:19:53.000Z", 
                "started_at": "2020-09-01T07:19:53.000Z", 
                "conclusion": "success"
            }
        ], 
        "head_sha": "59d31ad37dd761b4fb7be8a093397df976b285ac", 
        "started_at": "2020-09-01T07:19:25Z", 
        "id": 1054969873, 
        "conclusion": "failure"
    }, 
    {
        "status": "completed", 
        "check_run_url": "https://api.github.com/repos/drodin-tests/hunter/check-runs/1054969855", 
        "name": "libogg android-ndk-r17-api-24-arm64-v8a-clang-libcxx14 ubuntu-16.04", 
        "run_id": 233928809, 
        "url": "https://api.github.com/repos/drodin-tests/hunter/actions/jobs/1054969855", 
        "html_url": "https://github.com/drodin-tests/hunter/runs/1054969855", 
        "completed_at": "2020-09-01T07:20:42Z", 
        "run_url": "https://api.github.com/repos/drodin-tests/hunter/actions/runs/233928809", 
        "node_id": "MDg6Q2hlY2tSdW4xMDU0OTY5ODU1", 
        "steps": [
            {
                "status": "completed", 
                "name": "Set up job", 
                "number": 1, 
                "completed_at": "2020-09-01T07:19:26.000Z", 
                "started_at": "2020-09-01T07:19:23.000Z", 
                "conclusion": "success"
            }, 
            {
                "status": "completed", 
                "name": "Git checkout with submodules", 
                "number": 2, 
                "completed_at": "2020-09-01T07:19:30.000Z", 
                "started_at": "2020-09-01T07:19:26.000Z", 
                "conclusion": "success"
            }, 
            {
                "status": "completed", 
                "name": "Set up Python", 
                "number": 3, 
                "completed_at": "2020-09-01T07:19:30.000Z", 
                "started_at": "2020-09-01T07:19:30.000Z", 
                "conclusion": "success"
            }, 
            {
                "status": "completed", 
                "name": "Upgrade pip", 
                "number": 4, 
                "completed_at": "2020-09-01T07:19:31.000Z", 
                "started_at": "2020-09-01T07:19:30.000Z", 
                "conclusion": "success"
            }, 
            {
                "status": "completed", 
                "name": "Build on Unix", 
                "number": 5, 
                "completed_at": "2020-09-01T07:20:42.000Z", 
                "started_at": "2020-09-01T07:19:31.000Z", 
                "conclusion": "success"
            }, 
            {
                "status": "completed", 
                "name": "Build on Windows", 
                "number": 6, 
                "completed_at": "2020-09-01T07:20:42.000Z", 
                "started_at": "2020-09-01T07:20:42.000Z", 
                "conclusion": "skipped"
            }, 
            {
                "status": "completed", 
                "name": "Post Git checkout with submodules", 
                "number": 12, 
                "completed_at": "2020-09-01T07:20:42.000Z", 
                "started_at": "2020-09-01T07:20:42.000Z", 
                "conclusion": "success"
            }, 
            {
                "status": "completed", 
                "name": "Complete job", 
                "number": 13, 
                "completed_at": "2020-09-01T07:20:42.000Z", 
                "started_at": "2020-09-01T07:20:42.000Z", 
                "conclusion": "success"
            }
        ], 
        "head_sha": "59d31ad37dd761b4fb7be8a093397df976b285ac", 
        "started_at": "2020-09-01T07:19:23Z", 
        "id": 1054969855, 
        "conclusion": "success"
    }, 
    {
        "status": "completed", 
        "check_run_url": "https://api.github.com/repos/drodin-tests/hunter/check-runs/1054969824", 
        "name": "libogg clang-cxx17 ubuntu-16.04", 
        "run_id": 233928809, 
        "url": "https://api.github.com/repos/drodin-tests/hunter/actions/jobs/1054969824", 
        "html_url": "https://github.com/drodin-tests/hunter/runs/1054969824", 
        "completed_at": "2020-09-01T07:19:49Z", 
        "run_url": "https://api.github.com/repos/drodin-tests/hunter/actions/runs/233928809", 
        "node_id": "MDg6Q2hlY2tSdW4xMDU0OTY5ODI0", 
        "steps": [
            {
                "status": "completed", 
                "name": "Set up job", 
                "number": 1, 
                "completed_at": "2020-09-01T07:19:26.000Z", 
                "started_at": "2020-09-01T07:19:23.000Z", 
                "conclusion": "success"
            }, 
            {
                "status": "completed", 
                "name": "Git checkout with submodules", 
                "number": 2, 
                "completed_at": "2020-09-01T07:19:30.000Z", 
                "started_at": "2020-09-01T07:19:26.000Z", 
                "conclusion": "success"
            }, 
            {
                "status": "completed", 
                "name": "Set up Python", 
                "number": 3, 
                "completed_at": "2020-09-01T07:19:30.000Z", 
                "started_at": "2020-09-01T07:19:30.000Z", 
                "conclusion": "success"
            }, 
            {
                "status": "completed", 
                "name": "Upgrade pip", 
                "number": 4, 
                "completed_at": "2020-09-01T07:19:31.000Z", 
                "started_at": "2020-09-01T07:19:30.000Z", 
                "conclusion": "success"
            }, 
            {
                "status": "completed", 
                "name": "Build on Unix", 
                "number": 5, 
                "completed_at": "2020-09-01T07:19:49.000Z", 
                "started_at": "2020-09-01T07:19:31.000Z", 
                "conclusion": "success"
            }, 
            {
                "status": "completed", 
                "name": "Build on Windows", 
                "number": 6, 
                "completed_at": "2020-09-01T07:19:49.000Z", 
                "started_at": "2020-09-01T07:19:49.000Z", 
                "conclusion": "skipped"
            }, 
            {
                "status": "completed", 
                "name": "Post Git checkout with submodules", 
                "number": 12, 
                "completed_at": "2020-09-01T07:19:49.000Z", 
                "started_at": "2020-09-01T07:19:49.000Z", 
                "conclusion": "success"
            }, 
            {
                "status": "completed", 
                "name": "Complete job", 
                "number": 13, 
                "completed_at": "2020-09-01T07:19:49.000Z", 
                "started_at": "2020-09-01T07:19:49.000Z", 
                "conclusion": "success"
            }
        ], 
        "head_sha": "59d31ad37dd761b4fb7be8a093397df976b285ac", 
        "started_at": "2020-09-01T07:19:23Z", 
        "id": 1054969824, 
        "conclusion": "success"
    }, 
    {
        "status": "completed", 
        "check_run_url": "https://api.github.com/repos/drodin-tests/hunter/check-runs/1054969837", 
        "name": "libogg gcc-7-cxx17 ubuntu-16.04", 
        "run_id": 233928809, 
        "url": "https://api.github.com/repos/drodin-tests/hunter/actions/jobs/1054969837", 
        "html_url": "https://github.com/drodin-tests/hunter/runs/1054969837", 
        "completed_at": "2020-09-01T07:19:50Z", 
        "run_url": "https://api.github.com/repos/drodin-tests/hunter/actions/runs/233928809", 
        "node_id": "MDg6Q2hlY2tSdW4xMDU0OTY5ODM3", 
        "steps": [
            {
                "status": "completed", 
                "name": "Set up job", 
                "number": 1, 
                "completed_at": "2020-09-01T07:19:27.000Z", 
                "started_at": "2020-09-01T07:19:24.000Z", 
                "conclusion": "success"
            }, 
            {
                "status": "completed", 
                "name": "Git checkout with submodules", 
                "number": 2, 
                "completed_at": "2020-09-01T07:19:32.000Z", 
                "started_at": "2020-09-01T07:19:27.000Z", 
                "conclusion": "success"
            }, 
            {
                "status": "completed", 
                "name": "Set up Python", 
                "number": 3, 
                "completed_at": "2020-09-01T07:19:32.000Z", 
                "started_at": "2020-09-01T07:19:32.000Z", 
                "conclusion": "success"
            }, 
            {
                "status": "completed", 
                "name": "Upgrade pip", 
                "number": 4, 
                "completed_at": "2020-09-01T07:19:33.000Z", 
                "started_at": "2020-09-01T07:19:32.000Z", 
                "conclusion": "success"
            }, 
            {
                "status": "completed", 
                "name": "Build on Unix", 
                "number": 5, 
                "completed_at": "2020-09-01T07:19:50.000Z", 
                "started_at": "2020-09-01T07:19:33.000Z", 
                "conclusion": "success"
            }, 
            {
                "status": "completed", 
                "name": "Build on Windows", 
                "number": 6, 
                "completed_at": "2020-09-01T07:19:50.000Z", 
                "started_at": "2020-09-01T07:19:50.000Z", 
                "conclusion": "skipped"
            }, 
            {
                "status": "completed", 
                "name": "Post Git checkout with submodules", 
                "number": 12, 
                "completed_at": "2020-09-01T07:19:50.000Z", 
                "started_at": "2020-09-01T07:19:50.000Z", 
                "conclusion": "success"
            }, 
            {
                "status": "completed", 
                "name": "Complete job", 
                "number": 13, 
                "completed_at": "2020-09-01T07:19:50.000Z", 
                "started_at": "2020-09-01T07:19:50.000Z", 
                "conclusion": "success"
            }
        ], 
        "head_sha": "59d31ad37dd761b4fb7be8a093397df976b285ac", 
        "started_at": "2020-09-01T07:19:24Z", 
        "id": 1054969837, 
        "conclusion": "success"
    }, 
    {
        "status": "completed", 
        "check_run_url": "https://api.github.com/repos/drodin-tests/hunter/check-runs/1054969970", 
        "name": "libogg ios-nocodesign-13-2-dep-9-3 macos-10.15", 
        "run_id": 233928809, 
        "url": "https://api.github.com/repos/drodin-tests/hunter/actions/jobs/1054969970", 
        "html_url": "https://github.com/drodin-tests/hunter/runs/1054969970", 
        "completed_at": "2020-09-01T07:24:30Z", 
        "run_url": "https://api.github.com/repos/drodin-tests/hunter/actions/runs/233928809", 
        "node_id": "MDg6Q2hlY2tSdW4xMDU0OTY5OTcw", 
        "steps": [
            {
                "status": "completed", 
                "name": "Set up job", 
                "number": 1, 
                "completed_at": "2020-09-01T07:19:33.000Z", 
                "started_at": "2020-09-01T07:19:31.000Z", 
                "conclusion": "success"
            }, 
            {
                "status": "completed", 
                "name": "Git checkout with submodules", 
                "number": 2, 
                "completed_at": "2020-09-01T07:19:39.000Z", 
                "started_at": "2020-09-01T07:19:33.000Z", 
                "conclusion": "success"
            }, 
            {
                "status": "completed", 
                "name": "Set up Python", 
                "number": 3, 
                "completed_at": "2020-09-01T07:19:39.000Z", 
                "started_at": "2020-09-01T07:19:39.000Z", 
                "conclusion": "success"
            }, 
            {
                "status": "completed", 
                "name": "Upgrade pip", 
                "number": 4, 
                "completed_at": "2020-09-01T07:19:42.000Z", 
                "started_at": "2020-09-01T07:19:39.000Z", 
                "conclusion": "success"
            }, 
            {
                "status": "completed", 
                "name": "Build on Unix", 
                "number": 5, 
                "completed_at": "2020-09-01T07:24:29.000Z", 
                "started_at": "2020-09-01T07:19:42.000Z", 
                "conclusion": "success"
            }, 
            {
                "status": "completed", 
                "name": "Build on Windows", 
                "number": 6, 
                "completed_at": "2020-09-01T07:24:29.000Z", 
                "started_at": "2020-09-01T07:24:29.000Z", 
                "conclusion": "skipped"
            }, 
            {
                "status": "completed", 
                "name": "Post Git checkout with submodules", 
                "number": 12, 
                "completed_at": "2020-09-01T07:24:30.000Z", 
                "started_at": "2020-09-01T07:24:29.000Z", 
                "conclusion": "success"
            }, 
            {
                "status": "completed", 
                "name": "Complete job", 
                "number": 13, 
                "completed_at": "2020-09-01T07:24:30.000Z", 
                "started_at": "2020-09-01T07:24:30.000Z", 
                "conclusion": "success"
            }
        ], 
        "head_sha": "59d31ad37dd761b4fb7be8a093397df976b285ac", 
        "started_at": "2020-09-01T07:19:31Z", 
        "id": 1054969970, 
        "conclusion": "success"
    }, 
    {
        "status": "completed", 
        "check_run_url": "https://api.github.com/repos/drodin-tests/hunter/check-runs/1054970102", 
        "name": "libogg mingw-cxx17 windows-2016", 
        "run_id": 233928809, 
        "url": "https://api.github.com/repos/drodin-tests/hunter/actions/jobs/1054970102", 
        "html_url": "https://github.com/drodin-tests/hunter/runs/1054970102", 
        "completed_at": "2020-09-01T07:21:35Z", 
        "run_url": "https://api.github.com/repos/drodin-tests/hunter/actions/runs/233928809", 
        "node_id": "MDg6Q2hlY2tSdW4xMDU0OTcwMTAy", 
        "steps": [
            {
                "status": "completed", 
                "name": "Set up job", 
                "number": 1, 
                "completed_at": "2020-09-01T07:19:27.000Z", 
                "started_at": "2020-09-01T07:19:26.000Z", 
                "conclusion": "success"
            }, 
            {
                "status": "completed", 
                "name": "Git checkout with submodules", 
                "number": 2, 
                "completed_at": "2020-09-01T07:19:45.000Z", 
                "started_at": "2020-09-01T07:19:27.000Z", 
                "conclusion": "success"
            }, 
            {
                "status": "completed", 
                "name": "Set up Python", 
                "number": 3, 
                "completed_at": "2020-09-01T07:19:45.000Z", 
                "started_at": "2020-09-01T07:19:45.000Z", 
                "conclusion": "success"
            }, 
            {
                "status": "completed", 
                "name": "Upgrade pip", 
                "number": 4, 
                "completed_at": "2020-09-01T07:20:12.000Z", 
                "started_at": "2020-09-01T07:19:45.000Z", 
                "conclusion": "success"
            }, 
            {
                "status": "completed", 
                "name": "Build on Unix", 
                "number": 5, 
                "completed_at": "2020-09-01T07:20:12.000Z", 
                "started_at": "2020-09-01T07:20:12.000Z", 
                "conclusion": "skipped"
            }, 
            {
                "status": "completed", 
                "name": "Build on Windows", 
                "number": 6, 
                "completed_at": "2020-09-01T07:21:31.000Z", 
                "started_at": "2020-09-01T07:20:12.000Z", 
                "conclusion": "success"
            }, 
            {
                "status": "completed", 
                "name": "Post Git checkout with submodules", 
                "number": 12, 
                "completed_at": "2020-09-01T07:21:35.000Z", 
                "started_at": "2020-09-01T07:21:31.000Z", 
                "conclusion": "success"
            }, 
            {
                "status": "completed", 
                "name": "Complete job", 
                "number": 13, 
                "completed_at": "2020-09-01T07:21:35.000Z", 
                "started_at": "2020-09-01T07:21:35.000Z", 
                "conclusion": "success"
            }
        ], 
        "head_sha": "59d31ad37dd761b4fb7be8a093397df976b285ac", 
        "started_at": "2020-09-01T07:19:26Z", 
        "id": 1054970102, 
        "conclusion": "success"
    }, 
    {
        "status": "completed", 
        "check_run_url": "https://api.github.com/repos/drodin-tests/hunter/check-runs/1054970123", 
        "name": "libogg msys-cxx17 windows-2016", 
        "run_id": 233928809, 
        "url": "https://api.github.com/repos/drodin-tests/hunter/actions/jobs/1054970123", 
        "html_url": "https://github.com/drodin-tests/hunter/runs/1054970123", 
        "completed_at": "2020-09-01T07:23:03Z", 
        "run_url": "https://api.github.com/repos/drodin-tests/hunter/actions/runs/233928809", 
        "node_id": "MDg6Q2hlY2tSdW4xMDU0OTcwMTIz", 
        "steps": [
            {
                "status": "completed", 
                "name": "Set up job", 
                "number": 1, 
                "completed_at": "2020-09-01T07:19:30.000Z", 
                "started_at": "2020-09-01T07:19:27.000Z", 
                "conclusion": "success"
            }, 
            {
                "status": "completed", 
                "name": "Git checkout with submodules", 
                "number": 2, 
                "completed_at": "2020-09-01T07:19:48.000Z", 
                "started_at": "2020-09-01T07:19:30.000Z", 
                "conclusion": "success"
            }, 
            {
                "status": "completed", 
                "name": "Set up Python", 
                "number": 3, 
                "completed_at": "2020-09-01T07:19:48.000Z", 
                "started_at": "2020-09-01T07:19:48.000Z", 
                "conclusion": "success"
            }, 
            {
                "status": "completed", 
                "name": "Upgrade pip", 
                "number": 4, 
                "completed_at": "2020-09-01T07:20:16.000Z", 
                "started_at": "2020-09-01T07:19:48.000Z", 
                "conclusion": "success"
            }, 
            {
                "status": "completed", 
                "name": "Build on Unix", 
                "number": 5, 
                "completed_at": "2020-09-01T07:20:16.000Z", 
                "started_at": "2020-09-01T07:20:16.000Z", 
                "conclusion": "skipped"
            }, 
            {
                "status": "completed", 
                "name": "Build on Windows", 
                "number": 6, 
                "completed_at": "2020-09-01T07:23:00.000Z", 
                "started_at": "2020-09-01T07:20:16.000Z", 
                "conclusion": "success"
            }, 
            {
                "status": "completed", 
                "name": "Post Git checkout with submodules", 
                "number": 12, 
                "completed_at": "2020-09-01T07:23:03.000Z", 
                "started_at": "2020-09-01T07:23:00.000Z", 
                "conclusion": "success"
            }, 
            {
                "status": "completed", 
                "name": "Complete job", 
                "number": 13, 
                "completed_at": "2020-09-01T07:23:03.000Z", 
                "started_at": "2020-09-01T07:23:03.000Z", 
                "conclusion": "success"
            }
        ], 
        "head_sha": "59d31ad37dd761b4fb7be8a093397df976b285ac", 
        "started_at": "2020-09-01T07:19:27Z", 
        "id": 1054970123, 
        "conclusion": "success"
    }, 
    {
        "status": "completed", 
        "check_run_url": "https://api.github.com/repos/drodin-tests/hunter/check-runs/1054969986", 
        "name": "libogg ninja-vs-15-2017-win64-cxx17 windows-2016", 
        "run_id": 233928809, 
        "url": "https://api.github.com/repos/drodin-tests/hunter/actions/jobs/1054969986", 
        "html_url": "https://github.com/drodin-tests/hunter/runs/1054969986", 
        "completed_at": "2020-09-01T07:21:38Z", 
        "run_url": "https://api.github.com/repos/drodin-tests/hunter/actions/runs/233928809", 
        "node_id": "MDg6Q2hlY2tSdW4xMDU0OTY5OTg2", 
        "steps": [
            {
                "status": "completed", 
                "name": "Set up job", 
                "number": 1, 
                "completed_at": "2020-09-01T07:19:29.000Z", 
                "started_at": "2020-09-01T07:19:26.000Z", 
                "conclusion": "success"
            }, 
            {
                "status": "completed", 
                "name": "Git checkout with submodules", 
                "number": 2, 
                "completed_at": "2020-09-01T07:19:46.000Z", 
                "started_at": "2020-09-01T07:19:29.000Z", 
                "conclusion": "success"
            }, 
            {
                "status": "completed", 
                "name": "Set up Python", 
                "number": 3, 
                "completed_at": "2020-09-01T07:19:46.000Z", 
                "started_at": "2020-09-01T07:19:46.000Z", 
                "conclusion": "success"
            }, 
            {
                "status": "completed", 
                "name": "Upgrade pip", 
                "number": 4, 
                "completed_at": "2020-09-01T07:20:13.000Z", 
                "started_at": "2020-09-01T07:19:46.000Z", 
                "conclusion": "success"
            }, 
            {
                "status": "completed", 
                "name": "Build on Unix", 
                "number": 5, 
                "completed_at": "2020-09-01T07:20:13.000Z", 
                "started_at": "2020-09-01T07:20:13.000Z", 
                "conclusion": "skipped"
            }, 
            {
                "status": "completed", 
                "name": "Build on Windows", 
                "number": 6, 
                "completed_at": "2020-09-01T07:21:35.000Z", 
                "started_at": "2020-09-01T07:20:13.000Z", 
                "conclusion": "success"
            }, 
            {
                "status": "completed", 
                "name": "Post Git checkout with submodules", 
                "number": 12, 
                "completed_at": "2020-09-01T07:21:38.000Z", 
                "started_at": "2020-09-01T07:21:35.000Z", 
                "conclusion": "success"
            }, 
            {
                "status": "completed", 
                "name": "Complete job", 
                "number": 13, 
                "completed_at": "2020-09-01T07:21:38.000Z", 
                "started_at": "2020-09-01T07:21:38.000Z", 
                "conclusion": "success"
            }
        ], 
        "head_sha": "59d31ad37dd761b4fb7be8a093397df976b285ac", 
        "started_at": "2020-09-01T07:19:26Z", 
        "id": 1054969986, 
        "conclusion": "success"
    }, 
    {
        "status": "completed", 
        "check_run_url": "https://api.github.com/repos/drodin-tests/hunter/check-runs/1054970019", 
        "name": "libogg nmake-vs-15-2017-win64-cxx17 windows-2016", 
        "run_id": 233928809, 
        "url": "https://api.github.com/repos/drodin-tests/hunter/actions/jobs/1054970019", 
        "html_url": "https://github.com/drodin-tests/hunter/runs/1054970019", 
        "completed_at": "2020-09-01T07:21:42Z", 
        "run_url": "https://api.github.com/repos/drodin-tests/hunter/actions/runs/233928809", 
        "node_id": "MDg6Q2hlY2tSdW4xMDU0OTcwMDE5", 
        "steps": [
            {
                "status": "completed", 
                "name": "Set up job", 
                "number": 1, 
                "completed_at": "2020-09-01T07:19:30.000Z", 
                "started_at": "2020-09-01T07:19:27.000Z", 
                "conclusion": "success"
            }, 
            {
                "status": "completed", 
                "name": "Git checkout with submodules", 
                "number": 2, 
                "completed_at": "2020-09-01T07:19:47.000Z", 
                "started_at": "2020-09-01T07:19:30.000Z", 
                "conclusion": "success"
            }, 
            {
                "status": "completed", 
                "name": "Set up Python", 
                "number": 3, 
                "completed_at": "2020-09-01T07:19:47.000Z", 
                "started_at": "2020-09-01T07:19:47.000Z", 
                "conclusion": "success"
            }, 
            {
                "status": "completed", 
                "name": "Upgrade pip", 
                "number": 4, 
                "completed_at": "2020-09-01T07:20:15.000Z", 
                "started_at": "2020-09-01T07:19:47.000Z", 
                "conclusion": "success"
            }, 
            {
                "status": "completed", 
                "name": "Build on Unix", 
                "number": 5, 
                "completed_at": "2020-09-01T07:20:15.000Z", 
                "started_at": "2020-09-01T07:20:15.000Z", 
                "conclusion": "skipped"
            }, 
            {
                "status": "completed", 
                "name": "Build on Windows", 
                "number": 6, 
                "completed_at": "2020-09-01T07:21:39.000Z", 
                "started_at": "2020-09-01T07:20:15.000Z", 
                "conclusion": "success"
            }, 
            {
                "status": "completed", 
                "name": "Post Git checkout with submodules", 
                "number": 12, 
                "completed_at": "2020-09-01T07:21:42.000Z", 
                "started_at": "2020-09-01T07:21:39.000Z", 
                "conclusion": "success"
            }, 
            {
                "status": "completed", 
                "name": "Complete job", 
                "number": 13, 
                "completed_at": "2020-09-01T07:21:42.000Z", 
                "started_at": "2020-09-01T07:21:42.000Z", 
                "conclusion": "success"
            }
        ], 
        "head_sha": "59d31ad37dd761b4fb7be8a093397df976b285ac", 
        "started_at": "2020-09-01T07:19:27Z", 
        "id": 1054970019, 
        "conclusion": "success"
    }, 
    {
        "status": "completed", 
        "check_run_url": "https://api.github.com/repos/drodin-tests/hunter/check-runs/1054969954", 
        "name": "libogg osx-10-13-cxx14 macos-10.15", 
        "run_id": 233928809, 
        "url": "https://api.github.com/repos/drodin-tests/hunter/actions/jobs/1054969954", 
        "html_url": "https://github.com/drodin-tests/hunter/runs/1054969954", 
        "completed_at": "2020-09-01T07:22:07Z", 
        "run_url": "https://api.github.com/repos/drodin-tests/hunter/actions/runs/233928809", 
        "node_id": "MDg6Q2hlY2tSdW4xMDU0OTY5OTU0", 
        "steps": [
            {
                "status": "completed", 
                "name": "Set up job", 
                "number": 1, 
                "completed_at": "2020-09-01T07:19:32.000Z", 
                "started_at": "2020-09-01T07:19:31.000Z", 
                "conclusion": "success"
            }, 
            {
                "status": "completed", 
                "name": "Git checkout with submodules", 
                "number": 2, 
                "completed_at": "2020-09-01T07:19:39.000Z", 
                "started_at": "2020-09-01T07:19:32.000Z", 
                "conclusion": "success"
            }, 
            {
                "status": "completed", 
                "name": "Set up Python", 
                "number": 3, 
                "completed_at": "2020-09-01T07:19:39.000Z", 
                "started_at": "2020-09-01T07:19:39.000Z", 
                "conclusion": "success"
            }, 
            {
                "status": "completed", 
                "name": "Upgrade pip", 
                "number": 4, 
                "completed_at": "2020-09-01T07:19:41.000Z", 
                "started_at": "2020-09-01T07:19:39.000Z", 
                "conclusion": "success"
            }, 
            {
                "status": "completed", 
                "name": "Build on Unix", 
                "number": 5, 
                "completed_at": "2020-09-01T07:22:07.000Z", 
                "started_at": "2020-09-01T07:19:41.000Z", 
                "conclusion": "success"
            }, 
            {
                "status": "completed", 
                "name": "Build on Windows", 
                "number": 6, 
                "completed_at": "2020-09-01T07:22:07.000Z", 
                "started_at": "2020-09-01T07:22:07.000Z", 
                "conclusion": "skipped"
            }, 
            {
                "status": "completed", 
                "name": "Post Git checkout with submodules", 
                "number": 12, 
                "completed_at": "2020-09-01T07:22:07.000Z", 
                "started_at": "2020-09-01T07:22:07.000Z", 
                "conclusion": "success"
            }, 
            {
                "status": "completed", 
                "name": "Complete job", 
                "number": 13, 
                "completed_at": "2020-09-01T07:22:07.000Z", 
                "started_at": "2020-09-01T07:22:07.000Z", 
                "conclusion": "success"
            }
        ], 
        "head_sha": "59d31ad37dd761b4fb7be8a093397df976b285ac", 
        "started_at": "2020-09-01T07:19:31Z", 
        "id": 1054969954, 
        "conclusion": "success"
    }, 
    {
        "status": "completed", 
        "check_run_url": "https://api.github.com/repos/drodin-tests/hunter/check-runs/1054969935", 
        "name": "libogg osx-10-13-make-cxx14 macos-10.15", 
        "run_id": 233928809, 
        "url": "https://api.github.com/repos/drodin-tests/hunter/actions/jobs/1054969935", 
        "html_url": "https://github.com/drodin-tests/hunter/runs/1054969935", 
        "completed_at": "2020-09-01T07:21:24Z", 
        "run_url": "https://api.github.com/repos/drodin-tests/hunter/actions/runs/233928809", 
        "node_id": "MDg6Q2hlY2tSdW4xMDU0OTY5OTM1", 
        "steps": [
            {
                "status": "completed", 
                "name": "Set up job", 
                "number": 1, 
                "completed_at": "2020-09-01T07:19:31.000Z", 
                "started_at": "2020-09-01T07:19:29.000Z", 
                "conclusion": "success"
            }, 
            {
                "status": "completed", 
                "name": "Git checkout with submodules", 
                "number": 2, 
                "completed_at": "2020-09-01T07:19:38.000Z", 
                "started_at": "2020-09-01T07:19:31.000Z", 
                "conclusion": "success"
            }, 
            {
                "status": "completed", 
                "name": "Set up Python", 
                "number": 3, 
                "completed_at": "2020-09-01T07:19:38.000Z", 
                "started_at": "2020-09-01T07:19:38.000Z", 
                "conclusion": "success"
            }, 
            {
                "status": "completed", 
                "name": "Upgrade pip", 
                "number": 4, 
                "completed_at": "2020-09-01T07:19:40.000Z", 
                "started_at": "2020-09-01T07:19:38.000Z", 
                "conclusion": "success"
            }, 
            {
                "status": "completed", 
                "name": "Build on Unix", 
                "number": 5, 
                "completed_at": "2020-09-01T07:21:23.000Z", 
                "started_at": "2020-09-01T07:19:40.000Z", 
                "conclusion": "success"
            }, 
            {
                "status": "completed", 
                "name": "Build on Windows", 
                "number": 6, 
                "completed_at": "2020-09-01T07:21:23.000Z", 
                "started_at": "2020-09-01T07:21:23.000Z", 
                "conclusion": "skipped"
            }, 
            {
                "status": "completed", 
                "name": "Post Git checkout with submodules", 
                "number": 12, 
                "completed_at": "2020-09-01T07:21:23.000Z", 
                "started_at": "2020-09-01T07:21:23.000Z", 
                "conclusion": "success"
            }, 
            {
                "status": "completed", 
                "name": "Complete job", 
                "number": 13, 
                "completed_at": "2020-09-01T07:21:24.000Z", 
                "started_at": "2020-09-01T07:21:23.000Z", 
                "conclusion": "success"
            }
        ], 
        "head_sha": "59d31ad37dd761b4fb7be8a093397df976b285ac", 
        "started_at": "2020-09-01T07:19:29Z", 
        "id": 1054969935, 
        "conclusion": "success"
    }, 
    {
        "status": "completed", 
        "check_run_url": "https://api.github.com/repos/drodin-tests/hunter/check-runs/1054969882", 
        "name": "libogg sanitize-address-cxx17 ubuntu-16.04", 
        "run_id": 233928809, 
        "url": "https://api.github.com/repos/drodin-tests/hunter/actions/jobs/1054969882", 
        "html_url": "https://github.com/drodin-tests/hunter/runs/1054969882", 
        "completed_at": "2020-09-01T07:19:57Z", 
        "run_url": "https://api.github.com/repos/drodin-tests/hunter/actions/runs/233928809", 
        "node_id": "MDg6Q2hlY2tSdW4xMDU0OTY5ODgy", 
        "steps": [
            {
                "status": "completed", 
                "name": "Set up job", 
                "number": 1, 
                "completed_at": "2020-09-01T07:19:27.000Z", 
                "started_at": "2020-09-01T07:19:24.000Z", 
                "conclusion": "success"
            }, 
            {
                "status": "completed", 
                "name": "Git checkout with submodules", 
                "number": 2, 
                "completed_at": "2020-09-01T07:19:31.000Z", 
                "started_at": "2020-09-01T07:19:27.000Z", 
                "conclusion": "success"
            }, 
            {
                "status": "completed", 
                "name": "Set up Python", 
                "number": 3, 
                "completed_at": "2020-09-01T07:19:31.000Z", 
                "started_at": "2020-09-01T07:19:31.000Z", 
                "conclusion": "success"
            }, 
            {
                "status": "completed", 
                "name": "Upgrade pip", 
                "number": 4, 
                "completed_at": "2020-09-01T07:19:32.000Z", 
                "started_at": "2020-09-01T07:19:31.000Z", 
                "conclusion": "success"
            }, 
            {
                "status": "completed", 
                "name": "Build on Unix", 
                "number": 5, 
                "completed_at": "2020-09-01T07:19:56.000Z", 
                "started_at": "2020-09-01T07:19:32.000Z", 
                "conclusion": "success"
            }, 
            {
                "status": "completed", 
                "name": "Build on Windows", 
                "number": 6, 
                "completed_at": "2020-09-01T07:19:56.000Z", 
                "started_at": "2020-09-01T07:19:56.000Z", 
                "conclusion": "skipped"
            }, 
            {
                "status": "completed", 
                "name": "Post Git checkout with submodules", 
                "number": 12, 
                "completed_at": "2020-09-01T07:19:57.000Z", 
                "started_at": "2020-09-01T07:19:56.000Z", 
                "conclusion": "success"
            }, 
            {
                "status": "completed", 
                "name": "Complete job", 
                "number": 13, 
                "completed_at": "2020-09-01T07:19:57.000Z", 
                "started_at": "2020-09-01T07:19:57.000Z", 
                "conclusion": "success"
            }
        ], 
        "head_sha": "59d31ad37dd761b4fb7be8a093397df976b285ac", 
        "started_at": "2020-09-01T07:19:24Z", 
        "id": 1054969882, 
        "conclusion": "success"
    }, 
    {
        "status": "completed", 
        "check_run_url": "https://api.github.com/repos/drodin-tests/hunter/check-runs/1054969902", 
        "name": "libogg sanitize-leak-cxx17 ubuntu-16.04", 
        "run_id": 233928809, 
        "url": "https://api.github.com/repos/drodin-tests/hunter/actions/jobs/1054969902", 
        "html_url": "https://github.com/drodin-tests/hunter/runs/1054969902", 
        "completed_at": "2020-09-01T07:19:57Z", 
        "run_url": "https://api.github.com/repos/drodin-tests/hunter/actions/runs/233928809", 
        "node_id": "MDg6Q2hlY2tSdW4xMDU0OTY5OTAy", 
        "steps": [
            {
                "status": "completed", 
                "name": "Set up job", 
                "number": 1, 
                "completed_at": "2020-09-01T07:19:30.000Z", 
                "started_at": "2020-09-01T07:19:27.000Z", 
                "conclusion": "success"
            }, 
            {
                "status": "completed", 
                "name": "Git checkout with submodules", 
                "number": 2, 
                "completed_at": "2020-09-01T07:19:34.000Z", 
                "started_at": "2020-09-01T07:19:30.000Z", 
                "conclusion": "success"
            }, 
            {
                "status": "completed", 
                "name": "Set up Python", 
                "number": 3, 
                "completed_at": "2020-09-01T07:19:34.000Z", 
                "started_at": "2020-09-01T07:19:34.000Z", 
                "conclusion": "success"
            }, 
            {
                "status": "completed", 
                "name": "Upgrade pip", 
                "number": 4, 
                "completed_at": "2020-09-01T07:19:35.000Z", 
                "started_at": "2020-09-01T07:19:34.000Z", 
                "conclusion": "success"
            }, 
            {
                "status": "completed", 
                "name": "Build on Unix", 
                "number": 5, 
                "completed_at": "2020-09-01T07:19:57.000Z", 
                "started_at": "2020-09-01T07:19:35.000Z", 
                "conclusion": "success"
            }, 
            {
                "status": "completed", 
                "name": "Build on Windows", 
                "number": 6, 
                "completed_at": "2020-09-01T07:19:57.000Z", 
                "started_at": "2020-09-01T07:19:57.000Z", 
                "conclusion": "skipped"
            }, 
            {
                "status": "completed", 
                "name": "Post Git checkout with submodules", 
                "number": 12, 
                "completed_at": "2020-09-01T07:19:57.000Z", 
                "started_at": "2020-09-01T07:19:57.000Z", 
                "conclusion": "success"
            }, 
            {
                "status": "completed", 
                "name": "Complete job", 
                "number": 13, 
                "completed_at": "2020-09-01T07:19:57.000Z", 
                "started_at": "2020-09-01T07:19:57.000Z", 
                "conclusion": "success"
            }
        ], 
        "head_sha": "59d31ad37dd761b4fb7be8a093397df976b285ac", 
        "started_at": "2020-09-01T07:19:27Z", 
        "id": 1054969902, 
        "conclusion": "success"
    }, 
    {
        "status": "completed", 
        "check_run_url": "https://api.github.com/repos/drodin-tests/hunter/check-runs/1054969920", 
        "name": "libogg sanitize-thread-cxx17 ubuntu-16.04", 
        "run_id": 233928809, 
        "url": "https://api.github.com/repos/drodin-tests/hunter/actions/jobs/1054969920", 
        "html_url": "https://github.com/drodin-tests/hunter/runs/1054969920", 
        "completed_at": "2020-09-01T07:20:19Z", 
        "run_url": "https://api.github.com/repos/drodin-tests/hunter/actions/runs/233928809", 
        "node_id": "MDg6Q2hlY2tSdW4xMDU0OTY5OTIw", 
        "steps": [
            {
                "status": "completed", 
                "name": "Set up job", 
                "number": 1, 
                "completed_at": "2020-09-01T07:19:29.000Z", 
                "started_at": "2020-09-01T07:19:26.000Z", 
                "conclusion": "success"
            }, 
            {
                "status": "completed", 
                "name": "Git checkout with submodules", 
                "number": 2, 
                "completed_at": "2020-09-01T07:19:33.000Z", 
                "started_at": "2020-09-01T07:19:29.000Z", 
                "conclusion": "success"
            }, 
            {
                "status": "completed", 
                "name": "Set up Python", 
                "number": 3, 
                "completed_at": "2020-09-01T07:19:33.000Z", 
                "started_at": "2020-09-01T07:19:33.000Z", 
                "conclusion": "success"
            }, 
            {
                "status": "completed", 
                "name": "Upgrade pip", 
                "number": 4, 
                "completed_at": "2020-09-01T07:19:39.000Z", 
                "started_at": "2020-09-01T07:19:33.000Z", 
                "conclusion": "success"
            }, 
            {
                "status": "completed", 
                "name": "Build on Unix", 
                "number": 5, 
                "completed_at": "2020-09-01T07:20:19.000Z", 
                "started_at": "2020-09-01T07:19:39.000Z", 
                "conclusion": "success"
            }, 
            {
                "status": "completed", 
                "name": "Build on Windows", 
                "number": 6, 
                "completed_at": "2020-09-01T07:20:19.000Z", 
                "started_at": "2020-09-01T07:20:19.000Z", 
                "conclusion": "skipped"
            }, 
            {
                "status": "completed", 
                "name": "Post Git checkout with submodules", 
                "number": 12, 
                "completed_at": "2020-09-01T07:20:19.000Z", 
                "started_at": "2020-09-01T07:20:19.000Z", 
                "conclusion": "success"
            }, 
            {
                "status": "completed", 
                "name": "Complete job", 
                "number": 13, 
                "completed_at": "2020-09-01T07:20:19.000Z", 
                "started_at": "2020-09-01T07:20:19.000Z", 
                "conclusion": "success"
            }
        ], 
        "head_sha": "59d31ad37dd761b4fb7be8a093397df976b285ac", 
        "started_at": "2020-09-01T07:19:26Z", 
        "id": 1054969920, 
        "conclusion": "success"
    }, 
    {
        "status": "completed", 
        "check_run_url": "https://api.github.com/repos/drodin-tests/hunter/check-runs/1054970073", 
        "name": "libogg vs-14-2015-sdk-8-1 windows-2016", 
        "run_id": 233928809, 
        "url": "https://api.github.com/repos/drodin-tests/hunter/actions/jobs/1054970073", 
        "html_url": "https://github.com/drodin-tests/hunter/runs/1054970073", 
        "completed_at": "2020-09-01T07:25:01Z", 
        "run_url": "https://api.github.com/repos/drodin-tests/hunter/actions/runs/233928809", 
        "node_id": "MDg6Q2hlY2tSdW4xMDU0OTcwMDcz", 
        "steps": [
            {
                "status": "completed", 
                "name": "Set up job", 
                "number": 1, 
                "completed_at": "2020-09-01T07:19:29.000Z", 
                "started_at": "2020-09-01T07:19:28.000Z", 
                "conclusion": "success"
            }, 
            {
                "status": "completed", 
                "name": "Git checkout with submodules", 
                "number": 2, 
                "completed_at": "2020-09-01T07:19:47.000Z", 
                "started_at": "2020-09-01T07:19:29.000Z", 
                "conclusion": "success"
            }, 
            {
                "status": "completed", 
                "name": "Set up Python", 
                "number": 3, 
                "completed_at": "2020-09-01T07:19:47.000Z", 
                "started_at": "2020-09-01T07:19:47.000Z", 
                "conclusion": "success"
            }, 
            {
                "status": "completed", 
                "name": "Upgrade pip", 
                "number": 4, 
                "completed_at": "2020-09-01T07:20:13.000Z", 
                "started_at": "2020-09-01T07:19:47.000Z", 
                "conclusion": "success"
            }, 
            {
                "status": "completed", 
                "name": "Build on Unix", 
                "number": 5, 
                "completed_at": "2020-09-01T07:20:13.000Z", 
                "started_at": "2020-09-01T07:20:13.000Z", 
                "conclusion": "skipped"
            }, 
            {
                "status": "completed", 
                "name": "Build on Windows", 
                "number": 6, 
                "completed_at": "2020-09-01T07:24:58.000Z", 
                "started_at": "2020-09-01T07:20:13.000Z", 
                "conclusion": "success"
            }, 
            {
                "status": "completed", 
                "name": "Post Git checkout with submodules", 
                "number": 12, 
                "completed_at": "2020-09-01T07:25:01.000Z", 
                "started_at": "2020-09-01T07:24:58.000Z", 
                "conclusion": "success"
            }, 
            {
                "status": "completed", 
                "name": "Complete job", 
                "number": 13, 
                "completed_at": "2020-09-01T07:25:01.000Z", 
                "started_at": "2020-09-01T07:25:01.000Z", 
                "conclusion": "success"
            }
        ], 
        "head_sha": "59d31ad37dd761b4fb7be8a093397df976b285ac", 
        "started_at": "2020-09-01T07:19:28Z", 
        "id": 1054970073, 
        "conclusion": "success"
    }, 
    {
        "status": "completed", 
        "check_run_url": "https://api.github.com/repos/drodin-tests/hunter/check-runs/1054970048", 
        "name": "libogg vs-15-2017-win64-cxx17 windows-2016", 
        "run_id": 233928809, 
        "url": "https://api.github.com/repos/drodin-tests/hunter/actions/jobs/1054970048", 
        "html_url": "https://github.com/drodin-tests/hunter/runs/1054970048", 
        "completed_at": "2020-09-01T07:24:36Z", 
        "run_url": "https://api.github.com/repos/drodin-tests/hunter/actions/runs/233928809", 
        "node_id": "MDg6Q2hlY2tSdW4xMDU0OTcwMDQ4", 
        "steps": [
            {
                "status": "completed", 
                "name": "Set up job", 
                "number": 1, 
                "completed_at": "2020-09-01T07:19:31.000Z", 
                "started_at": "2020-09-01T07:19:27.000Z", 
                "conclusion": "success"
            }, 
            {
                "status": "completed", 
                "name": "Git checkout with submodules", 
                "number": 2, 
                "completed_at": "2020-09-01T07:19:46.000Z", 
                "started_at": "2020-09-01T07:19:31.000Z", 
                "conclusion": "success"
            }, 
            {
                "status": "completed", 
                "name": "Set up Python", 
                "number": 3, 
                "completed_at": "2020-09-01T07:19:46.000Z", 
                "started_at": "2020-09-01T07:19:46.000Z", 
                "conclusion": "success"
            }, 
            {
                "status": "completed", 
                "name": "Upgrade pip", 
                "number": 4, 
                "completed_at": "2020-09-01T07:20:07.000Z", 
                "started_at": "2020-09-01T07:19:46.000Z", 
                "conclusion": "success"
            }, 
            {
                "status": "completed", 
                "name": "Build on Unix", 
                "number": 5, 
                "completed_at": "2020-09-01T07:20:07.000Z", 
                "started_at": "2020-09-01T07:20:07.000Z", 
                "conclusion": "skipped"
            }, 
            {
                "status": "completed", 
                "name": "Build on Windows", 
                "number": 6, 
                "completed_at": "2020-09-01T07:24:33.000Z", 
                "started_at": "2020-09-01T07:20:07.000Z", 
                "conclusion": "success"
            }, 
            {
                "status": "completed", 
                "name": "Post Git checkout with submodules", 
                "number": 12, 
                "completed_at": "2020-09-01T07:24:36.000Z", 
                "started_at": "2020-09-01T07:24:33.000Z", 
                "conclusion": "success"
            }, 
            {
                "status": "completed", 
                "name": "Complete job", 
                "number": 13, 
                "completed_at": "2020-09-01T07:24:36.000Z", 
                "started_at": "2020-09-01T07:24:36.000Z", 
                "conclusion": "success"
            }
        ], 
        "head_sha": "59d31ad37dd761b4fb7be8a093397df976b285ac", 
        "started_at": "2020-09-01T07:19:27Z", 
        "id": 1054970048, 
        "conclusion": "success"
    }
]